plain_transformers/__init__.py
plain_transformers/yttm_tokenizer.py
plain_transformers/initializations/__init__.py
plain_transformers/initializations/initializations.py
plain_transformers/layers/__init__.py
plain_transformers/layers/common_layers.py
plain_transformers/layers/post_ln_decoder.py
plain_transformers/layers/post_ln_encoder.py
plain_transformers/layers/pre_ln_encoder.py
plain_transformers/layers/transformer_decoder.py
plain_transformers/layers/transformer_encoder.py
plain_transformers/layers/utils.py
plain_transformers/losses/__init__.py
plain_transformers/losses/label_smoothing_loss.py
plain_transformers/losses/unlikelihood_loss.py
plain_transformers/models/__init__.py
plain_transformers/models/multimodal_transformer.py
plain_transformers/models/transformer.py
plain_transformers/samplers/__init__.py
plain_transformers/samplers/base_sampler.py
plain_transformers/samplers/greedy_sampler.py
plain_transformers/samplers/nucleus_sampler.py
plain_transformers/schedulers/__init__.py
plain_transformers/schedulers/noam_scheduler.py
plain_transformers-0.0.1.6.dist-info/LICENSE
plain_transformers-0.0.1.6.dist-info/METADATA
plain_transformers-0.0.1.6.dist-info/WHEEL
plain_transformers-0.0.1.6.dist-info/top_level.txt
plain_transformers-0.0.1.6.dist-info/RECORD
