Metadata-Version: 2.1
Name: plain-transformers
Version: 0.0.1.6
Summary: one more transformers lib
Home-page: https://github.com/c00k1ez/plain_transformers
Author: c00k1ez
Author-email: c00k1ez.th13f@gmail.com
License: UNKNOWN
Project-URL: Bug Tracker, https://github.com/c00k1ez/plain_transformers/issues
Platform: UNKNOWN
Classifier: Programming Language :: Python :: 3
Classifier: License :: OSI Approved :: Apache Software License
Classifier: Operating System :: OS Independent
Requires-Python: >=3.6
Requires-Dist: torch (>=1.6.0)
Requires-Dist: youtokentome (>=1.0.6)
Requires-Dist: sentencepiece (==0.1.95)
Requires-Dist: pytest (==7.2.0)
